mcp_server_k8s/__init__.py
mcp_server_k8s/__main__.py
mcp_server_k8s/py.typed
mcp_server_k8s/server.py
mcp_server_k8s-0.1.2.dist-info/METADATA
mcp_server_k8s-0.1.2.dist-info/WHEEL
mcp_server_k8s-0.1.2.dist-info/RECORD
