Metadata-Version: 2.4
Name: mcp-server-k8s
Version: 0.1.2
Summary: Add your description here
Author-email: truskovskiyk <truskovskiyk@gmail.com>
Requires-Python: >=3.12
Requires-Dist: kubernetes>=32.0.1
